ragatouille/RAGPretrainedModel.py
ragatouille/RAGTrainer.py
ragatouille/__init__.py
ragatouille/utils.py
ragatouille/data/__init__.py
ragatouille/data/corpus_processor.py
ragatouille/data/preprocessors.py
ragatouille/data/training_data_processor.py
ragatouille/integrations/__init__.py
ragatouille/integrations/_langchain.py
ragatouille/models/__init__.py
ragatouille/models/base.py
ragatouille/models/colbert.py
ragatouille/models/index.py
ragatouille/models/torch_kmeans.py
ragatouille/models/utils.py
ragatouille/negative_miners/__init__.py
ragatouille/negative_miners/base.py
ragatouille/negative_miners/simpleminer.py
ragatouille-0.0.9.post2.dist-info/licenses/LICENSE
ragatouille-0.0.9.post2.dist-info/METADATA
ragatouille-0.0.9.post2.dist-info/WHEEL
ragatouille-0.0.9.post2.dist-info/top_level.txt
ragatouille-0.0.9.post2.dist-info/RECORD
