Metadata-Version: 2.4
Name: RAGatouille
Version: 0.0.9.post2
Summary: Library to facilitate the use of state-of-the-art retrieval models in common RAG contexts.
Author-email: Ben Clavié <bc@answer.ai>
Maintainer-email: Ben Clavié <bc@answer.ai>
License:                                  Apache License
Project-URL: Homepage, https://github.com/answerdotai/ragatouille
Keywords: reranking,retrieval,rag,nlp
License-File: LICENSE
Requires-Dist: llama-index
Requires-Dist: faiss-cpu
Requires-Dist: langchain_core
Requires-Dist: colbert-ai>=0.2.19
Requires-Dist: langchain
Requires-Dist: onnx
Requires-Dist: srsly
Requires-Dist: voyager
Requires-Dist: torch>=1.13
Requires-Dist: fast-pytorch-kmeans
Requires-Dist: sentence-transformers
Provides-Extra: all
Requires-Dist: llama-index; extra == "all"
Requires-Dist: langchain; extra == "all"
Requires-Dist: rerankers; extra == "all"
Requires-Dist: voyager; extra == "all"
Provides-Extra: llamaindex
Requires-Dist: llama-index; extra == "llamaindex"
Provides-Extra: langchain
Requires-Dist: langchain; extra == "langchain"
Provides-Extra: train
Requires-Dist: sentence-transformers; extra == "train"
Requires-Dist: pylate; extra == "train"
Requires-Dist: rerankers; extra == "train"
Dynamic: license-file
